wozpy/__init__.py
wozpy/models/models.py
wozpy/wozpy.py
wozpy-0.2.0.dist-info/LICENSE.md
wozpy-0.2.0.dist-info/METADATA
wozpy-0.2.0.dist-info/WHEEL
wozpy-0.2.0.dist-info/RECORD
