Metadata-Version: 2.1
Name: wozpy
Version: 0.2.0
Summary: Simple package to retrieve data from wozwaardeloket.nl
Author: wpeterw
Author-email: off@on.nl
Requires-Python: >=3.10,<4.0
Classifier: Programming Language :: Python :: 3
Classifier: Programming Language :: Python :: 3.10
Classifier: Programming Language :: Python :: 3.11
Classifier: Programming Language :: Python :: 3.12
Classifier: Programming Language :: Python :: 3.13
Requires-Dist: pydantic-settings (>=2.1.0,<3.0.0)
Requires-Dist: pydantic[extra] (>=2.9.2,<3.0.0)
Requires-Dist: pytest (>=7.4.4,<8.0.0)
Requires-Dist: pytest-cov (>=4.1.0,<5.0.0)
Requires-Dist: requests (>=2.31.0,<3.0.0)
Requires-Dist: requests-mock (>=1.11.0,<2.0.0)
